{"info":{"_postman_id":"4a423225-81bb-4cd6-87e0-fd51b798a3bf","name":"0repoTest1MOD","schema":"https://schema.getpostman.com/json/collection/v2.1.0/collection.json"},"item":[{"name":"Sample endpoint: Returns details about a particular user","id":"74c932a2-89eb-496f-a43c-3e8960dea50a","request":{"method":"GET","header":[],"url":{"raw":"{{baseUrl}}/user?id=-74922575","host":["{{baseUrl}}"],"path":["user"],"query":[{"key":"id","value":"-74922575","description":"(Required) ID of the user"}]}},"response":[{"id":"cea4aeab-7c07-4ab6-b6f6-574e967582b8","name":"Sample response: Details about a user by ID","originalRequest":{"method":"GET","header":[],"url":{"raw":"{{baseUrl}}/user?id=-74922575","host":["{{baseUrl}}"],"path":["user"],"query":[{"key":"id","value":"-74922575"}]}},"status":"OK","code":200,"_postman_previewlanguage":"json","header":[{"disabled":false,"description":"A link to the next page of responses","key":"x-next","value":"dolor id in est"},{"key":"Content-Type","value":"application/json"}],"cookie":[],"responseTime":null,"body":"{\n \"id\": 14852090,\n \"name\": \"minim in esse\",\n \"tag\": \"dolore irure exercitation\"\n}"},{"id":"8b724cb3-68a7-4dd0-9987-61fa67434bfc","name":"Unexpected error","originalRequest":{"method":"GET","header":[],"url":{"raw":"{{baseUrl}}/user?id=-74922575","host":["{{baseUrl}}"],"path":["user"],"query":[{"key":"id","value":"-74922575"}]}},"status":"Internal Server Error","code":500,"_postman_previewlanguage":"json","header":[{"key":"Content-Type","value":"application/json"}],"cookie":[],"responseTime":null,"body":"{\n \"code\": -49870990,\n \"message\": \"esse in\"\n}"}]}],"variable":[{"id":"61765c13-a908-44e3-a1df-8bd3840e012d","key":"baseUrl","value":"http://localhost:3000","type":"string"}]}
